iautil/__init__.py
iautil/io.py
iautil/plotting/__init__.py
iautil/plotting/image_tool/__init__.py
iautil/plotting/image_tool/controller.py
iautil/plotting/image_tool/slicing.py
iautil/utilities/__init__.py
iautil/utilities/ui.py
image_analysis_util-0.1.3.dist-info/LICENSE
image_analysis_util-0.1.3.dist-info/METADATA
image_analysis_util-0.1.3.dist-info/WHEEL
image_analysis_util-0.1.3.dist-info/top_level.txt
image_analysis_util-0.1.3.dist-info/RECORD
