Metadata-Version: 2.1
Name: image-analysis-util
Version: 0.1.3
Summary: Scientific image exploration software for multidimensional datasets.
Home-page: https://github.com/henryjsmith12/image-analysis-util
Author: Henry Smith
Author-email: smithh@anl.gov
License: See LICENSE file
Platform: any
License-File: LICENSE
Requires-Dist: h5py
Requires-Dist: numpy
Requires-Dist: PyQt5
Requires-Dist: pyqtgraph
Requires-Dist: scipy
Requires-Dist: vtk
Requires-Dist: xarray
